{
  "description": "test for case 6734",
  "owner": "bien",
  "preloadCounter": 2,
  "priority": "0",
  "processingType": "TRIGGER",
  "statisticMethod": "MEDIAN",
  "statisticPeriod": "ALL",
  "triggerType": "SCHEDULE",
  "customFieldValues": {
  },
  "items": 
  [
    {
      "name": "6262_Test_WF",
      "processingTemplate": "6262_Test_WF",
      "processingType": "WORKFLOW",
      "statisticMethod": "MEDIAN",
      "statisticPeriod": "ALL",
      "workflowType": "STANDARD"
    }
  ],
  "timeTriggers": 
  [
    {
      "calendar": "MONDAY_TO_FRIDAY",
      "endTime": 86399999,
      "repeatInterval": 3600000,
      "startTime": 36000000,
      "timeTriggerType": "DAILY",
      "timeZone": "Europe/Warsaw"
    }
  ]
}